odoo/addons/ebill_postfinance_server_env/README.rst
odoo/addons/ebill_postfinance_server_env/__init__.py
odoo/addons/ebill_postfinance_server_env/__manifest__.py
odoo/addons/ebill_postfinance_server_env/i18n/ebill_postfinance_server_env.pot
odoo/addons/ebill_postfinance_server_env/models/__init__.py
odoo/addons/ebill_postfinance_server_env/models/ebill_postfinance_service.py
odoo/addons/ebill_postfinance_server_env/readme/CONTRIBUTORS.rst
odoo/addons/ebill_postfinance_server_env/readme/DESCRIPTION.rst
odoo/addons/ebill_postfinance_server_env/static/description/icon.png
odoo/addons/ebill_postfinance_server_env/static/description/index.html
odoo_addon_ebill_postfinance_server_env-16.0.1.0.0.1.dist-info/METADATA
odoo_addon_ebill_postfinance_server_env-16.0.1.0.0.1.dist-info/WHEEL
odoo_addon_ebill_postfinance_server_env-16.0.1.0.0.1.dist-info/top_level.txt
odoo_addon_ebill_postfinance_server_env-16.0.1.0.0.1.dist-info/RECORD
