Metadata-Version: 2.1
Name: odoo-addon-ebill_postfinance_server_env
Version: 16.0.1.0.0.1
Summary: Server environment for eBill Postfinance
Home-page: https://github.com/OCA/l10n-switzerland
Author: Camptocamp, Odoo Community Association (OCA)
Author-email: support@odoo-community.org
License: AGPL-3
Classifier: Programming Language :: Python
Classifier: Framework :: Odoo
Classifier: Framework :: Odoo :: 16.0
Classifier: License :: OSI Approved :: GNU Affero General Public License v3
Requires-Python: >=3.10
Requires-Dist: odoo-addon-ebill-postfinance <16.1dev,>=16.0dev
Requires-Dist: odoo-addon-server-environment <16.1dev,>=16.0dev
Requires-Dist: odoo <16.1dev,>=16.0a
